dossier_competence/__init__.py
dossier_competence/anonyme.json
dossier_competence/cv.py
dossier_competence/export_config.py
dossier_competence/init_file.py
dossier_competence/main.py
dossier_competence/temp_cv.html
dossier_competence/webBlanche.html
dossier_competence/static/Datalyo_logo_rvb.png
dossier_competence/static/logo_pied.png
dossier_competence/static/pied.png
dossier_competence/static/test.css
test/__init__.py
test/test_export_config.py
test/test_main.py
dossiercompetence-1.2.4.dist-info/METADATA
dossiercompetence-1.2.4.dist-info/WHEEL
dossiercompetence-1.2.4.dist-info/entry_points.txt
dossiercompetence-1.2.4.dist-info/top_level.txt
dossiercompetence-1.2.4.dist-info/RECORD
