Metadata-Version: 2.1
Name: dossiercompetence
Version: 1.2.4
Summary: Anonymisation et filtrage des termes dans le CV, décoration et style des CV produits.
Home-page: https://gitlab-datalyo.francecentral.cloudapp.azure.com/dossier-de-comp-tences/dossiercompetence
Author: Xin Yao
Author-email: xin.yao@datalyo.com
License: UNKNOWN
Platform: UNKNOWN
Requires-Dist: Markdown
Requires-Dist: weasyprint
